[{ "value": "00" ,"text": "ไม่พิการ" },
{ "value": "06" ,"text": "ความบกพร่องทางการพูดและภาษา" },
{ "value": "01" ,"text": "ความบกพร่องทางการเห็น" },
{ "value": "02" ,"text": "ความบกพร่องทางการได้ยิน" },
{ "value": "04" ,"text": "ความบกพร่องทางร่างกายหรือสุขภาพ" },
{ "value": "03" ,"text": "ความบกพร่องทางสติปัญญา" },
{ "value": "09" ,"text": "บุคคลพิการซ้อน" },
{ "value": "05" ,"text": "มีปัญหาทางการเรียนรู้" },
{ "value": "07" ,"text": "มีปัญหาทางพฤติกรรม หรืออารมณ์" },
{ "value": "08" ,"text": "ออทิสติก" }]
